vretcity/constants.py
vretcity/exporter.py
vretcity/getters.py
vretcity/loader.py
vretcity/preprocessor.py
vretcity/visualisations.py
vretcity-0.1.1.dist-info/WHEEL
vretcity-0.1.1.dist-info/METADATA
vretcity-0.1.1.dist-info/RECORD
