Metadata-Version: 2.1
Name: vretcity
Version: 0.1.1
Summary: Package to preprocess and analyse data from the vretcity project at NUDZ
License: MIT
Author: Lukáš Hejtmánek
Author-email: hejtmy@gmail.com
Requires-Python: >=3.7,<4.0
Classifier: License :: OSI Approved :: MIT License
Classifier: Programming Language :: Python :: 3
Classifier: Programming Language :: Python :: 3.10
Classifier: Programming Language :: Python :: 3.7
Classifier: Programming Language :: Python :: 3.8
Classifier: Programming Language :: Python :: 3.9
Requires-Dist: numpy (>=1.20.0,<2.0.0)
Requires-Dist: pandas (>=1.3.3,<2.0.0)
Requires-Dist: plotly (>=5.3.1,<6.0.0)
